microservice_utils/__init__.py
microservice_utils/commands.py
microservice_utils/common.py
microservice_utils/constants.py
microservice_utils/events.py
microservice_utils/events_v1.py
microservice_utils/graphql.py
microservice_utils/py.typed
microservice_utils/google_cloud/__init__.py
microservice_utils/google_cloud/models.py
microservice_utils/google_cloud/adapters/__init__.py
microservice_utils/google_cloud/adapters/cloud_logging.py
microservice_utils/google_cloud/adapters/cloud_run.py
microservice_utils/google_cloud/adapters/cloud_storage.py
microservice_utils/google_cloud/adapters/cloud_tasks.py
microservice_utils/google_cloud/adapters/pubsub.py
microservice_utils/mandrill/__init__.py
microservice_utils/mandrill/adapters.py
microservice_utils/novu/__init__.py
microservice_utils/novu/adapters.py
microservice_utils/openai/__init__.py
microservice_utils/openai/adapters.py
microservice_utils/pinecone/__init__.py
microservice_utils/pinecone/adapters.py
microservice_utils/pinecone/utils.py
microservice_utils/telnyx/__init__.py
microservice_utils/telnyx/client.py
microservice_utils-0.13.23.dist-info/licenses/LICENSE
tests/__init__.py
tests/graphql.py
tests/test_commands.py
tests/test_events.py
tests/test_events_v1.py
tests/test_telnyx_client.py
tests/google_cloud/__init__.py
tests/google_cloud/test_cloud_run.py
tests/google_cloud/test_cloud_tasks.py
tests/novu/__init__.py
tests/novu/test_adapters.py
tests/openai/__init__.py
tests/openai/test_adapters.py
microservice_utils-0.13.23.dist-info/METADATA
microservice_utils-0.13.23.dist-info/WHEEL
microservice_utils-0.13.23.dist-info/top_level.txt
microservice_utils-0.13.23.dist-info/RECORD
