Metadata-Version: 2.4
Name: microservice-utils
Version: 0.13.23
License: MIT
Requires-Python: >=3.11
License-File: LICENSE
Requires-Dist: ulid-py<2,>=1
Requires-Dist: httpx==0.23.0
Provides-Extra: events
Requires-Dist: pydantic<2,>=1; extra == "events"
Provides-Extra: gcp-cloud-run
Requires-Dist: google-cloud-run<1; extra == "gcp-cloud-run"
Provides-Extra: gcp-cloud-tasks
Requires-Dist: google-cloud-tasks<3,>=2; extra == "gcp-cloud-tasks"
Provides-Extra: gcp-pubsub
Requires-Dist: google-cloud-pubsub<3,>=2; extra == "gcp-pubsub"
Requires-Dist: tenacity<9,>=8; extra == "gcp-pubsub"
Provides-Extra: gcp-storage
Requires-Dist: gcloud-aio-storage<9,>=8; extra == "gcp-storage"
Provides-Extra: novu
Requires-Dist: novu==1.11.0; extra == "novu"
Provides-Extra: openai
Requires-Dist: masked-ai<2,>=1; extra == "openai"
Requires-Dist: numpy<2,>=1; extra == "openai"
Requires-Dist: openai<1; extra == "openai"
Provides-Extra: pinecone
Requires-Dist: pinecone<8,>=6; extra == "pinecone"
Provides-Extra: nltk
Requires-Dist: nltk==3.9.1; extra == "nltk"
Provides-Extra: mailchimp-transactional
Requires-Dist: mailchimp-transactional==1.0.56; extra == "mailchimp-transactional"
Provides-Extra: sentence-transformers
Requires-Dist: sentence-transformers==5.0.0; extra == "sentence-transformers"
Dynamic: description
Dynamic: description-content-type
Dynamic: license
Dynamic: license-file
Dynamic: provides-extra
Dynamic: requires-dist
Dynamic: requires-python
